livekit/plugins/asyncai/__init__.py
livekit/plugins/asyncai/constants.py
livekit/plugins/asyncai/log.py
livekit/plugins/asyncai/models.py
livekit/plugins/asyncai/py.typed
livekit/plugins/asyncai/tts.py
livekit/plugins/asyncai/version.py
livekit_plugins_asyncai-1.2.15rc1.dist-info/METADATA
livekit_plugins_asyncai-1.2.15rc1.dist-info/WHEEL
livekit_plugins_asyncai-1.2.15rc1.dist-info/RECORD
