Metadata-Version: 2.4
Name: livekit-plugins-asyncai
Version: 1.2.15rc1
Summary: LiveKit Agents Plugin for AsyncAI
Project-URL: Documentation, https://docs.livekit.io
Project-URL: Source, https://github.com/livekit/agents
Project-URL: Website, https://livekit.io/
Author-email: LiveKit <hello@livekit.io>
License-Expression: Apache-2.0
Keywords: audio,livekit,realtime,video,webrtc
Classifier: Intended Audience :: Developers
Classifier: License :: OSI Approved :: Apache Software License
Classifier: Programming Language :: Python :: 3
Classifier: Programming Language :: Python :: 3 :: Only
Classifier: Programming Language :: Python :: 3.9
Classifier: Programming Language :: Python :: 3.10
Classifier: Topic :: Multimedia :: Sound/Audio
Classifier: Topic :: Multimedia :: Video
Classifier: Topic :: Scientific/Engineering :: Artificial Intelligence
Requires-Python: >=3.9.0
Requires-Dist: aiohttp
Requires-Dist: livekit-agents>=1.4.0.rc2
